fluent/runtime/__init__.py
fluent/runtime/builtins.py
fluent/runtime/bundle.py
fluent/runtime/errors.py
fluent/runtime/fallback.py
fluent/runtime/prepare.py
fluent/runtime/py.typed
fluent/runtime/resolver.py
fluent/runtime/types.py
fluent/runtime/utils.py
fluent.runtime-0.4.0.dist-info/METADATA
fluent.runtime-0.4.0.dist-info/WHEEL
fluent.runtime-0.4.0.dist-info/top_level.txt
fluent.runtime-0.4.0.dist-info/RECORD
