Metadata-Version: 2.1
Name: fluent.runtime
Version: 0.4.0
Summary: Localization library for expressive translations.
Home-page: https://github.com/projectfluent/python-fluent
Author: Luke Plant
Author-email: L.Plant.98@cantab.net
License: APL 2
Keywords: fluent,localization,l10n
Classifier: Development Status :: 3 - Alpha
Classifier: Intended Audience :: Developers
Classifier: License :: OSI Approved :: Apache Software License
Classifier: Programming Language :: Python :: 3.6
Classifier: Programming Language :: Python :: 3.7
Classifier: Programming Language :: Python :: 3.8
Classifier: Programming Language :: Python :: 3.9
Classifier: Programming Language :: Python :: 3 :: Only
